[
    {
        "codigo": "DSC0003",
        "nome": "DSC0003 - SAÚDE INDÍGENA",
        "turma": "01",
        "docente": "DENISE OSORIO SEVERO ",
        "horario": "3M1234 ",
        "qnt_vagas": "30",
        "local": "Sala de Metodologias Ativas do DSC/ULEG"
    },
    {
        "codigo": "DSC0007",
        "nome": "DSC0007 - INTRODUCAO A BIOETICA",
        "turma": "01",
        "docente": "CLAUDIO FORTES GARCIA LORENZO ",
        "horario": "3N12 ",
        "qnt_vagas": "50",
        "local": "BSA S BT 47/13"
    },
    {
        "codigo": "DSC0010",
        "nome": "DSC0010 - INFORMAÇÃO E INFORMÁTICA EM SAÚDE",
        "turma": "01",
        "docente": "MARCUS TOLENTINO SILVA ",
        "horario": "5N1234 ",
        "qnt_vagas": "40",
        "local": "BSA S A1 16/30"
    },
    {
        "codigo": "DSC0016",
        "nome": "DSC0016 - EDUCAÇÃO EM SAÚDE",
        "turma": "01",
        "docente": "THAIS BRANQUINHO OLIVEIRA FRAGELLI ",
        "horario": "5N1234 ",
        "qnt_vagas": "30",
        "local": "BSA S BT 11/13"
    },
    {
        "codigo": "DSC0020",
        "nome": "DSC0020 - EPIDEMIOLOGIA GERAL",
        "turma": "01",
        "docente": "EDGAR MERCHAN HAMANN ",
        "horario": "2T2345 Segunda-feira 14:00 às 17:50",
        "qnt_vagas": "32",
        "local": "BSA S B2 47/10"
    },
    {
        "codigo": "DSC0020",
        "nome": "DSC0020 - EPIDEMIOLOGIA GERAL",
        "turma": "02",
        "docente": "MAURO NISKIER SANCHEZ ",
        "horario": "4T2345 ",
        "qnt_vagas": "36",
        "local": "BSA S B1 41/13"
    },
    {
        "codigo": "DSC0037",
        "nome": "DSC0037 - PRATICAS DE SAUDE",
        "turma": "02",
        "docente": "THAIS BRANQUINHO OLIVEIRA FRAGELLI ",
        "horario": "3T2345 ",
        "qnt_vagas": "90",
        "local": "BSA S A2 16/22"
    },
    {
        "codigo": "DSC0038",
        "nome": "DSC0038 - SAUDE FAMILIAR",
        "turma": "01",
        "docente": "GIOVANNA ANGELA LEONEL OLIVEIRA ",
        "horario": "6N1234 ",
        "qnt_vagas": "30",
        "local": "BSA S B1 11/13"
    },
    {
        "codigo": "DSC0043",
        "nome": "DSC0043 - SAUDE MENTAL EM SAUDE COLETIVA",
        "turma": "01",
        "docente": "MUNA MUHAMMAD ODEH ",
        "horario": "4T234 Quarta-feira 14:00 às 16:55",
        "qnt_vagas": "30",
        "local": "ICC BT 016/62"
    },
    {
        "codigo": "DSC0045",
        "nome": "DSC0045 - VIGILANCIA SANITARIA",
        "turma": "01",
        "docente": "MARIA CAROLINA MESQUITA DOS SANTOS ",
        "horario": "3T2345 ",
        "qnt_vagas": "30",
        "local": "A DEFINIR"
    },
    {
        "codigo": "DSC0049",
        "nome": "DSC0049 - LABORATÓRIO DA ANTROPOLOGIA DA SAÚDE E DA DOENÇA",
        "turma": "01",
        "docente": "XIMENA PAMELA CLAUDIA DIAZ BERMUDEZ ",
        "horario": "4T2345 Quarta-feira 14:00 às 17:50",
        "qnt_vagas": "15",
        "local": "BSAS B2 21/14"
    },
    {
        "codigo": "DSC0050",
        "nome": "DSC0050 - POLÍTICAS PÚBLICAS EM SAÚDE",
        "turma": "01",
        "docente": "CARLO HENRIQUE GORETTI ZANETTI ",
        "horario": "4N1234 ",
        "qnt_vagas": "60",
        "local": "BSA S BT 41/10"
    },
    {
        "codigo": "DSC0051",
        "nome": "DSC0051 - DEMOGRAFIA E BIOESTATÍSTICA",
        "turma": "01",
        "docente": "MARCUS TOLENTINO SILVA ",
        "horario": "6N1234 ",
        "qnt_vagas": "40",
        "local": "BSA S A1 16/37"
    },
    {
        "codigo": "DSC0052",
        "nome": "DSC0052 - FUNDAMENTOS BIOLÓGICOS EM SAÚDE COLETIVA",
        "turma": "01",
        "docente": "JONAS LOTUFO BRANT DE CARVALHO ",
        "horario": "2N1234 Segunda-feira 19:00 às 22:30",
        "qnt_vagas": "60",
        "local": "BSA S B1 11/13"
    },
    {
        "codigo": "DSC0056",
        "nome": "DSC0056 - COMUNICAÇÃO EM SAÚDE",
        "turma": "01",
        "docente": "ANA VALERIA MACHADO MENDONCA ",
        "horario": "2N1234 Segunda-feira 19:00 às 22:30",
        "qnt_vagas": "50",
        "local": "BSA S B2 47/10"
    },
    {
        "codigo": "DSC0057",
        "nome": "DSC0057 - CIÊNCIAS SOCIAIS EM SAÚDE",
        "turma": "01",
        "docente": "EVERTON LUIS PEREIRA ",
        "horario": "5N1234 ",
        "qnt_vagas": "50",
        "local": "BSA S B2 54/13"
    },
    {
        "codigo": "DSC0058",
        "nome": "DSC0058 - FUNDAMENTOS BIOLÓGICOS EM SAÚDE COLETIVA 2",
        "turma": "01",
        "docente": "ISABELA RESENDE AVILA ",
        "horario": "2N1234 ",
        "qnt_vagas": "30",
        "local": "BSA S B1 54/10"
    },
    {
        "codigo": "DSC0061",
        "nome": "DSC0061 - FUNDAMENTOS BIOLÓGICOS EM SAÚDE COLETIVA 3",
        "turma": "01",
        "docente": "EDGAR MERCHAN HAMANN ",
        "horario": "3N1234 ",
        "qnt_vagas": "30",
        "local": "BSA S B2 41/13"
    },
    {
        "codigo": "DSC0062",
        "nome": "DSC0062 - PRÁTICAS INTEGRADAS EM SAÚDE COLETIVA 1",
        "turma": "02",
        "docente": "EVERTON LUIS PEREIRA ",
        "horario": "4N1234 ",
        "qnt_vagas": "30",
        "local": "A DEFINIR"
    },
    {
        "codigo": "DSC0063",
        "nome": "DSC0063 - DIREITO SANITÁRIO E LEGISLAÇÃO",
        "turma": "01",
        "docente": "GIOVANNA ANGELA LEONEL OLIVEIRA ",
        "horario": "2N12 ",
        "qnt_vagas": "30",
        "local": "BSA S B2 41/10"
    },
    {
        "codigo": "DSC0065",
        "nome": "DSC0065 - GESTÃO ESTRATÉGICA PARTICIPAÇÃO E CONTROLE SOCIAL EM SAÚDE",
        "turma": "01",
        "docente": "DENISE OSORIO SEVERO ",
        "horario": "3N1234 ",
        "qnt_vagas": "40",
        "local": "A DEFINIR"
    },
    {
        "codigo": "DSC0067",
        "nome": "DSC0067 - PRÁTICAS INTEGRADAS EM SAÚDE 2",
        "turma": "01",
        "docente": "ISABELA RESENDE AVILA ",
        "horario": "6N1234 ",
        "qnt_vagas": "60",
        "local": "A DEFINIR"
    },
    {
        "codigo": "DSC0069",
        "nome": "DSC0069 - EPIDEMIOLOGIA PARA A GESTÃO 3 VIGILÂNCIA EM SAÚDE",
        "turma": "01",
        "docente": "MAURO NISKIER SANCHEZ ",
        "horario": "2N1234 ",
        "qnt_vagas": "30",
        "local": "BSA S B1 47/10"
    },
    {
        "codigo": "DSC0070",
        "nome": "DSC0070 - MONITORAMENTO E AVALIAÇÃO EM SAÚDE",
        "turma": "01",
        "docente": "WALLACE ENRICO BOAVENTURA GONCALVES DOS SANTOS ",
        "horario": "5N1234 Quinta-feira 19:00 às 22:30",
        "qnt_vagas": "40",
        "local": "BSA S B1 34/10"
    },
    {
        "codigo": "DSC0072",
        "nome": "DSC0072 - GESTÃO DO TRABALHO E EDUCAÇÃO PERMANENTE NA SAÚDE",
        "turma": "01",
        "docente": "JOAO ANDRE SANTOS DE OLIVEIRA ",
        "horario": "5N1234 ",
        "qnt_vagas": "35",
        "local": "BSA S BT 54/13"
    },
    {
        "codigo": "DSC0073",
        "nome": "DSC0073 - TECNOLOGIAS PARA INFORMAÇÃO COMUNICAÇÃO EM SAÚDE",
        "turma": "01",
        "docente": "JOAO PAULO FERNANDES DA SILVA ",
        "horario": "3N1234 ",
        "qnt_vagas": "30",
        "local": "BSA S B1 41/10"
    },
    {
        "codigo": "DSC0074",
        "nome": "DSC0074 - SEMINÁRIO INTEGRADOR EM SAÚDE COLETIVA 1",
        "turma": "01",
        "docente": "ROSAMARIA GIATTI CARNEIRO ",
        "horario": "4N12 ",
        "qnt_vagas": "30",
        "local": "A DEFINIR"
    },
    {
        "codigo": "DSC0075",
        "nome": "DSC0075 - GESTÃO E PROMOÇÃO DA SAÚDE",
        "turma": "01",
        "docente": "DAIS GONCALVES ROCHA ",
        "horario": "3N1234 ",
        "qnt_vagas": "30",
        "local": "BSA S B2 54/10"
    },
    {
        "codigo": "DSC0076",
        "nome": "DSC0076 - SEMINÁRIO INTEGRADOR EM SAÚDE COLETIVA 2",
        "turma": "02",
        "docente": "DAIS GONCALVES ROCHA ",
        "horario": "5N12 ",
        "qnt_vagas": "30",
        "local": "A DEFINIR"
    },
    {
        "codigo": "DSC0078",
        "nome": "DSC0078 - SEMINÁRIO INTEGRADOR EM SAÚDE COLETIVA 3",
        "turma": "01",
        "docente": "ERICA LIMA COSTA DE MENEZES ",
        "horario": "4N123 ",
        "qnt_vagas": "30",
        "local": "BSA S B2 34/13"
    },
    {
        "codigo": "DSC0079",
        "nome": "DSC0079 - GESTÃO DE SISTEMAS E SERVIÇOS DE SAÚDE",
        "turma": "01",
        "docente": "JOAO ANDRE SANTOS DE OLIVEIRA ",
        "horario": "4N1234 ",
        "qnt_vagas": "30",
        "local": "BSA S B2 41/13"
    },
    {
        "codigo": "DSC0086",
        "nome": "DSC0086 - SAÚDE INTERNACIONAL - TÓPICOS ESPECIAIS EM SAÚDE COLETIVA",
        "turma": "01",
        "docente": "JONAS LOTUFO BRANT DE CARVALHO ",
        "horario": "4M1234 ",
        "qnt_vagas": "30",
        "local": "Sala de Metodologias Ativas do DSC/ULEG"
    },
    {
        "codigo": "DSC0090",
        "nome": "DSC0090 - EXTENSÃO EM SAÚDE",
        "turma": "03",
        "docente": "ANA VALERIA MACHADO MENDONCA ",
        "horario": "46T45 ",
        "qnt_vagas": "30",
        "local": "4T45(ICC BT 006) 6T45(BSA S AT 14/15)"
    },
    {
        "codigo": "DSC0090",
        "nome": "DSC0090 - EXTENSÃO EM SAÚDE",
        "turma": "04",
        "docente": "CLAUDIA MARA PEDROSA ",
        "horario": "5M1234 ",
        "qnt_vagas": "30",
        "local": "A DEFINIR"
    },
    {
        "codigo": "DSC0092",
        "nome": "DSC0092 - PLANEJAMENTO E PROGRAMAÇÃO EM SAÚDE",
        "turma": "01",
        "docente": "DENISE DE LIMA COSTA FURLANETTO ",
        "horario": "4N1234 Quarta-feira 19:00 às 22:30",
        "qnt_vagas": "30",
        "local": "BSA S B1 54/10"
    },
    {
        "codigo": "DSC0093",
        "nome": "DSC0093 - EPIDEMIOLOGIA DESCRITIVA",
        "turma": "01",
        "docente": "GIOVANNA ANGELA LEONEL OLIVEIRA ",
        "horario": "3N1234 Terça-feira 19:00 às 22:30",
        "qnt_vagas": "31",
        "local": "BSA S BT 41/13"
    },
    {
        "codigo": "DSC0094",
        "nome": "DSC0094 - TERAPIAS COMUNITÁRIAS E PRÁTICAS INTEGRATIVAS",
        "turma": "01",
        "docente": "CYNTHIA BISINOTO EVANGELISTA DE OLIVEIRA ",
        "horario": "3M34 ",
        "qnt_vagas": "40",
        "local": "Faculdade de Planaltina"
    },
    {
        "codigo": "DSC0094",
        "nome": "DSC0094 - TERAPIAS COMUNITÁRIAS E PRÁTICAS INTEGRATIVAS",
        "turma": "02",
        "docente": "DANIELA DA SILVA RODRIGUES ",
        "horario": "3M5 3T1 Terça-feira 12:00 às 13:50",
        "qnt_vagas": "35",
        "local": "UAC 04"
    },
    {
        "codigo": "DSC0094",
        "nome": "DSC0094 - TERAPIAS COMUNITÁRIAS E PRÁTICAS INTEGRATIVAS",
        "turma": "03",
        "docente": "JOSENAIDE ENGRACIA DOS SANTOS ",
        "horario": "4M5 4T1 ",
        "qnt_vagas": "36",
        "local": "UAC 04"
    },
    {
        "codigo": "DSC0095",
        "nome": "DSC0095 - EPIDEMIOLOGIA ANALÍTICA",
        "turma": "01",
        "docente": "IVAN RICARDO ZIMMERMANN ",
        "horario": "2N1234 Segunda-feira 19:00 às 22:30",
        "qnt_vagas": "30",
        "local": "BSA S B2 34/13"
    },
    {
        "codigo": "DSC0096",
        "nome": "DSC0096 - ECONOMIA DA SAÚDE",
        "turma": "01",
        "docente": "CARLO HENRIQUE GORETTI ZANETTI ",
        "horario": "5N1234 ",
        "qnt_vagas": "30",
        "local": "Sala de Metodologias Ativas do DSC/ULEG"
    },
    {
        "codigo": "DSC0099",
        "nome": "DSC0099 - TRABALHO DE CONCLUSÃO DE CURSO 1",
        "turma": "01",
        "docente": "ROSAMARIA GIATTI CARNEIRO ",
        "horario": "3N1234 ",
        "qnt_vagas": "30",
        "local": "BSA S B1 34/10"
    },
    {
        "codigo": "DSC0151",
        "nome": "DSC0151 - ANÁLISE DE POLÍTICAS DE SAÚDE I",
        "turma": "01",
        "docente": "HELENA ERI SHIMIZU ",
        "horario": "4T456 Quarta-feira 16:00 às 18:55",
        "qnt_vagas": "30",
        "local": "BSA S B1 19/13"
    },
    {
        "codigo": "DSC0156",
        "nome": "DSC0156 - EXTENSÃO EM PLANEJAMENTO E GESTÃO EM SAÚDE",
        "turma": "01",
        "docente": "DENISE DE LIMA COSTA FURLANETTO ",
        "horario": "5T2345 ",
        "qnt_vagas": "10",
        "local": "A DEFINIR"
    },
    {
        "codigo": "DSC0164",
        "nome": "DSC0164 - PRÁTICAS SUPERVISIONADAS EM SAÚDE COLETIVA II",
        "turma": "01",
        "docente": "XIMENA PAMELA CLAUDIA DIAZ BERMUDEZ ",
        "horario": "4N1234 ",
        "qnt_vagas": "30",
        "local": "Sala de Metodologias Ativas do DSC/ULEG"
    },
    {
        "codigo": "DSC0167",
        "nome": "DSC0167 - PRÁTICAS SUPERVISIONADAS EM SAÚDE COLETIVA III",
        "turma": "01",
        "docente": "CLAUDIO FORTES GARCIA LORENZO ",
        "horario": "4N1234 ",
        "qnt_vagas": "15",
        "local": "BSAS B2 21/9"
    },
    {
        "codigo": "DSC0171",
        "nome": "DSC0171 - TRABALHO DE CONCLUSÃO DE CURSO EM SAÚDE COLETIVA 2",
        "turma": "01",
        "docente": "MUNA MUHAMMAD ODEH ",
        "horario": "3N123 ",
        "qnt_vagas": "30",
        "local": "Sala de Metodologias Ativas do DSC/ULEG"
    },
    {
        "codigo": "DSC0172",
        "nome": "DSC0172 - VIGILÂNCIA EPIDEMIOLÓGICA PARTICIPATIVA",
        "turma": "01",
        "docente": "LIGIA MARIA CANTARINO DA COSTA ",
        "horario": "2M5 2T1 ",
        "qnt_vagas": "5500",
        "local": "a designar"
    }
]